genicam-1.5.0.data/purelib/genicam/README.rst
genicam-1.5.0.data/purelib/genicam/TLSimu.cti
genicam-1.5.0.data/purelib/genicam/__init__.py
genicam-1.5.0.data/purelib/genicam/_genapi.so
genicam-1.5.0.data/purelib/genicam/_gentl.so
genicam-1.5.0.data/purelib/genicam/genapi.py
genicam-1.5.0.data/purelib/genicam/gentl.py
genicam-1.5.0.data/purelib/genicam/libGCBase_clang140_v3_5.dylib
genicam-1.5.0.data/purelib/genicam/libGenApi_clang140_v3_5.dylib
genicam-1.5.0.data/purelib/genicam/libLog_clang140_v3_5.dylib
genicam-1.5.0.data/purelib/genicam/libMathParser_clang140_v3_5.dylib
genicam-1.5.0.data/purelib/genicam/libNodeMapData_clang140_v3_5.dylib
genicam-1.5.0.data/purelib/genicam/libVirtualFG.dylib
genicam-1.5.0.data/purelib/genicam/libXmlParser_clang140_v3_5.dylib
genicam-1.5.0.data/purelib/genicam/licenses/CLSerAll_LICENSE.txt
genicam-1.5.0.data/purelib/genicam/licenses/GenICam_License.pdf
genicam-1.5.0.data/purelib/genicam/licenses/LGPL.txt
genicam-1.5.0.data/purelib/genicam/licenses/MIT_License.txt
genicam-1.5.0.data/purelib/genicam/licenses/expat-COPYING.txt
genicam-1.5.0.data/purelib/genicam/licenses/genx-LICENSE.txt
genicam-1.5.0.data/purelib/genicam/licenses/miniz_LICENSE.txt
genicam-1.5.0.data/purelib/genicam/licenses/pcre2_License.txt
genicam-1.5.0.data/purelib/genicam/licenses/regexp-LICENSE.txt
genicam-1.5.0.data/purelib/genicam/licenses/xs3p_License.mht
genicam-1.5.0.data/purelib/genicam/licenses/xxhash_License.txt
genicam-1.5.0.data/purelib/genicam/licenses/zlib-LICENSE.txt
genicam-1.5.0.dist-info/LICENSE.txt
genicam-1.5.0.dist-info/METADATA
genicam-1.5.0.dist-info/WHEEL
genicam-1.5.0.dist-info/top_level.txt
genicam-1.5.0.dist-info/RECORD
