Metadata-Version: 2.1
Name: genicam
Version: 1.5.0
Summary: The official Python Binding for the GenICam GenApi & the GenTL Producers
Home-page: https://www.emva.org
Author: The GenICam Committee
Author-email: genicam@list.stemmer-imaging.com
License: The GenICam License Version 1.6
Download-URL: https://pypi.org/project/genicam/
Platform: UNKNOWN
Classifier: Development Status :: 5 - Production/Stable
Classifier: License :: Other/Proprietary License
Classifier: Operating System :: MacOS :: MacOS X
Classifier: Operating System :: Microsoft :: Windows
Classifier: Operating System :: POSIX
Classifier: Programming Language :: Python :: 3
Provides: genicam
